[
  {
    "CaseTypeID": "ET_Scotland",
    "ID": "addAmendClaimantRepresentative",
    "Name": "Claimant Representative",
    "Description": "Add or Amend a Claimant Representative",
    "DisplayOrder": 14,
    "PreConditionState(s)": "Accepted;Rejected;Closed",
    "PostConditionState": "*",
    "EventEnablingCondition": "managingOffice !=\"Unassigned\"",
    "SecurityClassification": "Public",
    "ShowEventNotes": "N",
    "ShowSummary": "N",
    "CallBackURLAboutToSubmitEvent": "${ET_COS_URL}/addAmendClaimantRepresentative/aboutToSubmit"
  }
]