{
  "local": {
    "ET_COS_URL": "http://host.docker.internal:8081",
    "CCD_DEF_URL": "http://host.docker.internal:4452",
    "CCD_DEF_AAC_URL": "http://host.docker.internal:4454"
  },
  "cftlib": {
    "ET_COS_URL": "http://localhost:8081",
    "CCD_DEF_URL": "http://localhost:4452",
    "CCD_DEF_AAC_URL": "http://localhost:4454"
  },
  "preview": {
    "ET_COS_URL": "https://et-cos-et-ccd-definitions-admin-pr-130.preview.platform.hmcts.net",
    "CCD_DEF_URL": "https://ccd-data-store-api-et-ccd-definitions-admin-pr-130.preview.platform.hmcts.net",
    "CCD_DEF_AAC_URL": "https://aac-et-ccd-definitions-admin-pr-130.preview.platform.hmcts.net"
  },
  "demo": {
    "ET_COS_URL": "http://et-cos-demo.service.core-compute-demo.internal",
    "CCD_DEF_URL": "http://ccd-data-store-api-demo.service.core-compute-demo.internal",
    "CCD_DEF_AAC_URL": "http://aac-manage-case-assignment-demo.service.core-compute-demo.internal"
  },
  "aat": {
    "ET_COS_URL": "http://et-cos-aat.service.core-compute-aat.internal",
    "CCD_DEF_URL": "http://ccd-data-store-api-aat.service.core-compute-aat.internal",
    "CCD_DEF_AAC_URL": "http://aac-manage-case-assignment-aat.service.core-compute-aat.internal"
  },
  "perftest": {
    "ET_COS_URL": "http://et-cos-perftest.service.core-compute-perftest.internal",
    "CCD_DEF_URL": "http://ccd-data-store-api-perftest.service.core-compute-perftest.internal",
    "CCD_DEF_AAC_URL": "http://aac-manage-case-assignment-perftest.service.core-compute-perftest.internal"
  },
  "prod": {
    "ET_COS_URL": "http://et-cos-prod.service.core-compute-prod.internal",
    "CCD_DEF_URL": "http://ccd-data-store-api-prod.service.core-compute-prod.internal",
    "CCD_DEF_AAC_URL": "http://aac-manage-case-assignment-prod.service.core-compute-prod.internal"
  },
  "ithc": {
    "ET_COS_URL": "http://et-cos-ithc.service.core-compute-ithc.internal",
    "CCD_DEF_URL": "http://ccd-data-store-api-ithc.service.core-compute-ithc.internal",
    "CCD_DEF_AAC_URL": "http://aac-manage-case-assignment-ithc.service.core-compute-ithc.internal"
  }
}
