[
  {
    "CaseTypeID": "ET_Scotland",
    "CaseEventID": "manageCaseTTL",
    "CaseFieldID": "TTL",
    "DisplayContext": "COMPLEX",
    "PageID": 11,
    "PageDisplayOrder": 11,
    "PageFieldDisplayOrder": 1,
    "ShowSummaryChangeOption": "Y",
    "PageColumnNumber": 1
  },
  {
    "CaseTypeID": "ET_Scotland",
    "CaseEventID": "amendCaseDetails",
    "CaseFieldID": "TTL",
    "DisplayContext": "COMPLEX",
    "PageID": 3,
    "PageDisplayOrder": 23,
    "PageFieldDisplayOrder": 3,
    "FieldShowCondition": "additionalCaseInfo.additional_live_appeal=\"Yes\" OR additionalCaseInfo.interventionRequired=\"Yes\"",
    "ShowSummaryChangeOption": "Y",
    "PageColumnNumber": 1
  },
  {
    "CaseTypeID": "ET_Scotland",
    "CaseEventID": "amendCaseDetailsClosed",
    "CaseFieldID": "TTL",
    "DisplayContext": "COMPLEX",
    "PageID": 2,
    "PageDisplayOrder": 2,
    "PageFieldDisplayOrder": 3,
    "FieldShowCondition": "additionalCaseInfo.additional_live_appeal=\"Yes\" OR additionalCaseInfo.interventionRequired=\"Yes\"",
    "ShowSummaryChangeOption": "Y",
    "PageColumnNumber": 1
  },
  {
    "CaseTypeID": "ET_Scotland",
    "CaseEventID": "disposeCase",
    "CaseFieldID": "additionalCaseInfo",
    "DisplayContext": "OPTIONAL",
    "PageID": 2,
    "PageDisplayOrder": 2,
    "PageFieldDisplayOrder": 7,
    "FieldShowCondition": "positionType =\"dummy\"",
    "ShowSummaryChangeOption": "Y",
    "PageColumnNumber": 1
  },
  {
    "CaseTypeID": "ET_Scotland",
    "CaseEventID": "disposeCase",
    "CaseFieldID": "TTL",
    "DisplayContext": "COMPLEX",
    "PageID": 2,
    "PageDisplayOrder": 2,
    "PageFieldDisplayOrder": 8,
    "ShowSummaryChangeOption": "Y",
    "FieldShowCondition": "additionalCaseInfo.additional_live_appeal=\"Yes\" OR additionalCaseInfo.interventionRequired=\"Yes\"",
    "PageColumnNumber": 1
  }
]
